LICENSE
MANIFEST.in
README.md
setup.cfg
setup.py
vcfped/__init__.py
vcfped/checkped.py
vcfped/vcfped.py
vcfped/vcfped_test.py
vcfped.egg-info/PKG-INFO
vcfped.egg-info/SOURCES.txt
vcfped.egg-info/dependency_links.txt
vcfped.egg-info/entry_points.txt
vcfped.egg-info/requires.txt
vcfped.egg-info/top_level.txt
vcfped/testfiles/trio.ped
vcfped/testfiles/trioHG002_22X.vcf