Metadata-Version: 1.1
Name: vcfped
Version: 1.3.1
Summary: Identification of trios and other close relationships in multisample VCF files
Home-page: https://github.com/magnusdv/vcfped
Author: Magnus Dehli Vigeland
Author-email: magnusdv@medisin.uio.no
License: GPL-2
Keywords: trio,relatedness,variant files,vcf,high-throughput sequencing,exome sequencing,family-based sequencing
Platform: UNKNOWN
Classifier: Programming Language :: Python :: 2.7
Classifier: License :: OSI Approved :: GNU General Public License v2 or later (GPLv2+)
